.gitignore
.travis.yml
CHANGES.txt
MANIFEST.in
README.rst
base.cfg
bootstrap.py
buildout.cfg
collective.readitlater-configure.zcml
omelette.cfg
setup.py
travis.cfg
collective/__init__.py
collective.readitlater.egg-info/PKG-INFO
collective.readitlater.egg-info/SOURCES.txt
collective.readitlater.egg-info/dependency_links.txt
collective.readitlater.egg-info/entry_points.txt
collective.readitlater.egg-info/namespace_packages.txt
collective.readitlater.egg-info/not-zip-safe
collective.readitlater.egg-info/requires.txt
collective.readitlater.egg-info/top_level.txt
collective/readitlater/__init__.py
collective/readitlater/configure.zcml
collective/readitlater/i18n.py
collective/readitlater/layer.py
collective/readitlater/registry.py
collective/readitlater/testing.py
collective/readitlater/upgrades.py
collective/readitlater/upgrades.zcml
collective/readitlater/vocabulary.py
collective/readitlater/browser/__init__.py
collective/readitlater/browser/add_url.py
collective/readitlater/browser/configure.zcml
collective/readitlater/browser/external.py
collective/readitlater/browser/view.py
collective/readitlater/browser/templates/iframe.pt
collective/readitlater/browser/templates/script.pt
collective/readitlater/browser/templates/show_all.pt
collective/readitlater/browser/templates/style.pt
collective/readitlater/browser/templates/urladded.pt
collective/readitlater/locales/collective.readitlater.pot
collective/readitlater/locales/en/LC_MESSAGES/collective.readitlater.po
collective/readitlater/locales/fr/LC_MESSAGES/collective.readitlater.po
collective/readitlater/profiles/default/browserlayer.xml
collective/readitlater/profiles/default/controlpanel.xml
collective/readitlater/profiles/default/metadata.xml
collective/readitlater/profiles/default/registry.xml
collective/readitlater/tests/__init__.py
collective/readitlater/tests/base.py
collective/readitlater/tests/test_setup.py